MANIFEST.in
README.txt
setup.py
OASYS1_SRW_SOLEIL.egg-info/PKG-INFO
OASYS1_SRW_SOLEIL.egg-info/SOURCES.txt
OASYS1_SRW_SOLEIL.egg-info/dependency_links.txt
OASYS1_SRW_SOLEIL.egg-info/entry_points.txt
OASYS1_SRW_SOLEIL.egg-info/namespace_packages.txt
OASYS1_SRW_SOLEIL.egg-info/not-zip-safe
OASYS1_SRW_SOLEIL.egg-info/requires.txt
OASYS1_SRW_SOLEIL.egg-info/top_level.txt
orangecontrib/__init__.py
orangecontrib/srw/__init__.py
orangecontrib/srw/soleil/__init__.py
orangecontrib/srw/soleil/widgets/__init__.py
orangecontrib/srw/soleil/widgets/light_sources/__init__.py
orangecontrib/srw/soleil/widgets/light_sources/ow_soleil_srw_bending_magnet.py
orangecontrib/srw/soleil/widgets/light_sources/ow_soleil_srw_power_density.py
orangecontrib/srw/soleil/widgets/light_sources/ow_soleil_srw_radiation.py
orangecontrib/srw/soleil/widgets/light_sources/ow_soleil_srw_spectrum.py
orangecontrib/srw/soleil/widgets/light_sources/icons/bending_magnet.png
orangecontrib/srw/soleil/widgets/light_sources/icons/power_density.png
orangecontrib/srw/soleil/widgets/light_sources/icons/radiation.png
orangecontrib/srw/soleil/widgets/light_sources/icons/source.png
orangecontrib/srw/soleil/widgets/light_sources/icons/spectrum.png
soleil/__init__.py
soleil/wofrysrw/__init__.py
soleil/wofrysrw/storage_ring/__init__.py
soleil/wofrysrw/storage_ring/light_sources/__init__.py
soleil/wofrysrw/storage_ring/light_sources/srw_infrared_light_source.py
soleil/wofrysrw/storage_ring/magnetic_structures/__init__.py
soleil/wofrysrw/storage_ring/magnetic_structures/srw_infrared_bending_magnet.py