Metadata-Version: 1.1
Name: OASYS1-SRW-SOLEIL
Version: 1.0.1
Summary: WIDGETS DEVELOPED BY SOLEIL TO EXTEND SRW FUNCTIONALITIES
Home-page: http://github.com/oasys-soleil-kit/OASYS1-SRW-SOLEIL
Author: Ferenc Borondics and Luca Rebuffi
Author-email: ferenc.borondics@synchrotron-soleil.fr
License: MIT
Download-URL: http://github.com/oasys-soleil-kit/OASYS1-SRW-SOLEIL
Keywords: ray-tracing,simulator,oasys1
Platform: UNKNOWN
Classifier: Development Status :: 4 - Beta
Classifier: Environment :: X11 Applications :: Qt
Classifier: Environment :: Console
Classifier: Environment :: Plugins
Classifier: Programming Language :: Cython
Classifier: Programming Language :: Python
Classifier: Programming Language :: Python :: 3
Classifier: Intended Audience :: Science/Research
